tenzir/__init__.py
tenzir/_bin/__init__.py
tenzir/_bin/_common.py
tenzir/_bin/tenzir.py
tenzir/_bin/tenzir_ctl.py
tenzir/_bin/tenzir_node.py
tenzir/bundled/bin/tenzir
tenzir/bundled/lib/systemd/system/tenzir-node.service
tenzir/bundled/libexec/tenzir-df-percent.sh
tenzir/bundled/libexec/uv
tenzir/bundled/share/doc/tenzir/LICENSE
tenzir/bundled/share/doc/tenzir/README.md
tenzir/bundled/share/doc/tenzir/VERSIONING.md
tenzir/bundled/share/doc/tenzir/examples/tenzir.yaml
tenzir/bundled/share/doc/tenzir/examples/plugin/amqp/amqp.yaml
tenzir/bundled/share/doc/tenzir/examples/plugin/compaction/compaction.yaml
tenzir/bundled/share/doc/tenzir/examples/plugin/compaction/tenzir.yaml
tenzir/bundled/share/doc/tenzir/examples/plugin/fluent-bit/fluent-bit.yaml
tenzir/bundled/share/doc/tenzir/examples/plugin/kafka/kafka.yaml
tenzir/bundled/share/doc/tenzir/examples/plugin/platform/platform.yaml
tenzir/bundled/share/tenzir/python/tenzir_common-5.25.1-py3-none-any.whl
tenzir/bundled/share/tenzir/python/tenzir_operator-5.25.1-py3-none-any.whl
tenzir/bundled/share/tenzir/schema/concepts/suricata.yaml
tenzir/bundled/share/tenzir/schema/concepts/sysmon.yaml
tenzir/bundled/share/tenzir/schema/concepts/zeek.yaml
tenzir/bundled/share/tenzir/schema/taxonomy/ecs/source.yaml
tenzir/bundled/share/tenzir/schema/taxonomy/tenzir/file.yaml
tenzir/bundled/share/tenzir/schema/taxonomy/tenzir/network.yaml
tenzir/bundled/share/tenzir/schema/taxonomy/tenzir/process.yaml
tenzir/bundled/share/tenzir/schema/types/argus.schema
tenzir/bundled/share/tenzir/schema/types/suricata.schema
tenzir/bundled/share/tenzir/schema/types/syslog.schema
tenzir/bundled/share/tenzir/schema/types/sysmon.schema
tenzir/bundled/share/tenzir/schema/types/test.schema
tenzir/bundled/share/tenzir/schema/types/zeek.schema
tenzir/bundled/share/tenzir/schema/types/ocsf/v1_0_0.schema
tenzir/bundled/share/tenzir/schema/types/ocsf/v1_1_0.schema
tenzir/bundled/share/tenzir/schema/types/ocsf/v1_2_0.schema
tenzir-5.25.1.dist-info/METADATA
tenzir-5.25.1.dist-info/WHEEL
tenzir-5.25.1.dist-info/entry_points.txt
tenzir-5.25.1.dist-info/top_level.txt
tenzir-5.25.1.dist-info/RECORD
