Metadata-Version: 2.4
Name: tenzir
Version: 5.25.1
Summary: Tenzir CLI bindings and binary launchers
Author-email: Tenzir <engineering@tenzir.com>
License-Expression: BSD-3-Clause
Project-URL: Homepage, https://tenzir.com
Project-URL: Documentation, https://docs.tenzir.com/reference/python-api
Project-URL: Repository, https://github.com/tenzir/tenzir
Classifier: Development Status :: 3 - Alpha
Classifier: Environment :: Plugins
Classifier: Operating System :: MacOS :: MacOS X
Classifier: Operating System :: POSIX :: Linux
Classifier: Topic :: Security
Classifier: Topic :: Scientific/Engineering :: Information Analysis
Classifier: Topic :: Scientific/Engineering :: Interface Engine/Protocol Translator
Classifier: Topic :: Software Development :: Object Brokering
Classifier: Topic :: System :: Distributed Computing
Requires-Python: >=3.9
Requires-Dist: numpy>=1.24
Requires-Dist: python-box>=7.3.2
Requires-Dist: tenzir-common<5.26.0,>=5.25.1
